jaq/__init__.py
jaq/py.typed
jaq/queues.py
jaq/store.py
jaq/threads.py
jaq_alkasm-1.2.0.dist-info/WHEEL
jaq_alkasm-1.2.0.dist-info/METADATA
jaq_alkasm-1.2.0.dist-info/RECORD
